pychesstools/.DS_Store
pychesstools/__init__.py
pychesstools/_cache.py
pychesstools/data/book.json
pychesstools/data/fischer_fens.fen
pychesstools/game.py
pychesstools/openings.py
pychesstools/pgn.py
pychesstools/position.py
pychesstools/py.typed
pychesstools/timer.py
pychesstools/types.py
pychesstools/utils.py
pychesstools/variants/__init__.py
pychesstools/variants/atomic.py
pychesstools/variants/crazyhouse.py
pychesstools/variants/horde.py
pychesstools/variants/king_of_the_hill.py
pychesstools/variants/three_check.py
pychesstools-0.1.27.dist-info/METADATA
pychesstools-0.1.27.dist-info/WHEEL
pychesstools-0.1.27.dist-info/RECORD
